LandSeed/ErrorHandling.py
LandSeed/LandSeed.py
LandSeed/LibPaths.py
LandSeed/ShaderFragmentInfoClass.py
LandSeed/TemplateInfoClass.py
LandSeed/__init__.py
LandSeed/data/Templates/classic_shader/output.frag
LandSeed/data/Templates/classic_shader/template.config
LandSeed/data/Templates/classic_shader/vertex_shader.vert
LandSeed/data/Templates/classic_shader/viewer.py
LandSeed/data/Templates/fancy_shader/output.frag
LandSeed/data/Templates/fancy_shader/template.config
LandSeed/data/Templates/fancy_shader/vertex_shader.vert
LandSeed/data/Templates/fancy_shader/viewer.py
LandSeed/data/Templates/heightmap/output.frag
LandSeed/data/Templates/heightmap/template.config
LandSeed/data/Templates/heightmap/vertex_shader.vert
LandSeed/data/Templates/heightmap/viewer.py
LandSeed/data/Templates/shadertoy/shadertoy.frag
LandSeed/data/Templates/shadertoy/template.config
LandSeed/data/Templates/shared/vertex_shader.vert
LandSeed/data/Templates/shared/viewer.py
LandSeed/data/shader_code/features/fbm_gradient.frag
LandSeed/data/shader_code/features/fbm_voronoi.frag
LandSeed/data/shader_code/features/phasor.frag
LandSeed/data/shader_code/features/plateau.frag
LandSeed/data/shader_code/features/valley.frag
LandSeed/data/shader_code/utils/gradient.frag
LandSeed/data/shader_code/utils/rand2.frag
LandSeed/data/shader_code/utils/rand3.frag
LandSeed/data/shader_code/utils/voronoi.frag
LandSeed/input/demo.frag
LandSeed/input/demo2.frag
LandSeed-1.0.13.dist-info/LICENSE
LandSeed-1.0.13.dist-info/METADATA
LandSeed-1.0.13.dist-info/WHEEL
LandSeed-1.0.13.dist-info/entry_points.txt
LandSeed-1.0.13.dist-info/top_level.txt
LandSeed-1.0.13.dist-info/RECORD
