Metadata-Version: 2.1
Name: LandSeed
Version: 1.0.13
Summary: Procedural terrain shader generator
Home-page: https://github.com/Sauww/LandSeed
Author: Bastien Zigmann
Author-email: bastien@zigmann.org
License: UNKNOWN
Platform: UNKNOWN
Classifier: Programming Language :: Python :: 3
Classifier: License :: OSI Approved :: MIT License
Classifier: Operating System :: POSIX :: Linux
Requires-Python: >=3.0
Requires-Dist: numpy (>=1.18.1)
Requires-Dist: glfw (>=1.11.1)
Requires-Dist: PyOpenGL (>=3.1.5)
